lotus_nlte/__init__.py
lotus_nlte/config.py
lotus_nlte/download.py
lotus_nlte/lotus_nlte_version.py
lotus_nlte/optimize.py
lotus_nlte/plot.py
lotus_nlte/sampling.py
lotus_nlte/utils.py
lotus_nlte/gcogs/__init__.py
lotus_nlte/gcogs/gcog.py
lotus_nlte/gcogs/multigcogs.py
lotus_nlte/gcogs/utils.py
lotus_nlte/interpolation/__init__.py
lotus_nlte/interpolation/gp_interp.py
lotus_nlte/interpolation/multipoly_interp.py
lotus_nlte/interpolation/rbf_interp.py
lotus_nlte/package_data/linelist/final.linelist
lotus_nlte/package_data/linelist/ges.linelist
lotus_nlte/package_data/linelist/metalpoor.linelist
lotus_nlte/test/data/HD122563.csv
lotus_nlte/test/data/Sun.csv
lotus_nlte/theano_op/__init__.py
lotus_nlte/theano_op/likelihood.py
lotus_nlte/theano_op/predict.py
lotus_nlte-0.1.1.dist-info/LICENSE
lotus_nlte-0.1.1.dist-info/METADATA
lotus_nlte-0.1.1.dist-info/WHEEL
lotus_nlte-0.1.1.dist-info/top_level.txt
lotus_nlte-0.1.1.dist-info/RECORD
