Metadata-Version: 2.1
Name: lotus-nlte
Version: 0.1.1
Summary: Determine atmospheric stellar parameters in non-LTE
Home-page: https://github.com/Li-Yangyang/LOTUs
Author: Yangyang Li
Author-email: ly95astro@gmail.com
Maintainer: Yangyang Li
License: MIT
Classifier: Development Status :: 2 - Pre-Alpha
Classifier: Intended Audience :: Developers
Classifier: Intended Audience :: Science/Research
Classifier: License :: OSI Approved :: MIT License
Classifier: Operating System :: OS Independent
Classifier: Programming Language :: Python :: 3.7
Requires-Python: >= 3.7, < 3.8
License-File: LICENSE
Requires-Dist: cython (==0.29.24)
Requires-Dist: numpy (>=1.16.4)
Requires-Dist: pandas (==0.24.2)
Requires-Dist: tables (==3.7.0)
Requires-Dist: scipy (>=1.5.0)
Requires-Dist: sympy (>=1.6.2)
Requires-Dist: h5py (>=2.10.0)
Requires-Dist: astropy (>=3.2.1)
Requires-Dist: joblib (==1.0.1)
Requires-Dist: numdifftools (==0.9.39)
Requires-Dist: scikit-learn (==0.23.2)
Requires-Dist: pymc3 (==3.7)
Requires-Dist: theano (==1.0.4)
Requires-Dist: matplotlib (>=3.1.3)
Requires-Dist: tqdm
Requires-Dist: corner
Requires-Dist: requests
Provides-Extra: advanced-interp
Requires-Dist: rbf ; extra == 'advanced-interp'
Requires-Dist: torch ; extra == 'advanced-interp'
Requires-Dist: gpytorch ; extra == 'advanced-interp'
Provides-Extra: doc
Requires-Dist: sphinx-book-theme ; extra == 'doc'
